mkdocs_embed_file_plugins/__init__.py
mkdocs_embed_file_plugins/plugin.py
mkdocs_embed_file_plugins/src/__init__.py
mkdocs_embed_file_plugins/src/links_correction.py
mkdocs_embed_file_plugins/src/search_quote.py
mkdocs_embed_file_plugins/src/utils.py
mkdocs_embed_file_plugin-2.1.4.dist-info/METADATA
mkdocs_embed_file_plugin-2.1.4.dist-info/WHEEL
mkdocs_embed_file_plugin-2.1.4.dist-info/entry_points.txt
mkdocs_embed_file_plugin-2.1.4.dist-info/licenses/LICENSE
mkdocs_embed_file_plugin-2.1.4.dist-info/RECORD
