Metadata-Version: 2.4
Name: mkdocs-embed-file-plugin
Version: 2.1.4
Summary: A plugin to quote file from docs
Project-URL: homepage, https://github.com/ObsidianPublisher/mkdocs-embed_file-plugin
Author-email: Mara-Li <mara-li@outlook.fr>
License-Expression: AGPL-3.0-or-later
License-File: LICENSE
Keywords: cite,embed,file,mkdocs,obsidian,obsidian.md,quote
Classifier: License :: OSI Approved :: GNU Affero General Public License v3 or later (AGPLv3+)
Classifier: Natural Language :: English
Classifier: Natural Language :: French
Classifier: Topic :: Text Processing :: Markup :: Markdown
Requires-Python: >=3.13
Requires-Dist: beautifulsoup4
Requires-Dist: markdown
Requires-Dist: mdx-wikilink-plus
Requires-Dist: mkdocs
Requires-Dist: mkdocs-callouts
Requires-Dist: mkdocs-custom-tags-attributes
Requires-Dist: pymdown-extensions
Requires-Dist: python-frontmatter
Requires-Dist: ruamel-yaml
Requires-Dist: setuptools
